bitchat/__init__.py
bitchat/ble_service.py
bitchat/channel.py
bitchat/compression.py
bitchat/delivery_tracker.py
bitchat/encryption.py
bitchat/keychain.py
bitchat/message.py
bitchat/protocol.py
bitchat/retention.py
bitchat/utils.py
bitchat-1.0.0.dist-info/LICENSE
bitchat-1.0.0.dist-info/METADATA
bitchat-1.0.0.dist-info/WHEEL
bitchat-1.0.0.dist-info/RECORD
