Metadata-Version: 2.3
Name: bitchat
Version: 1.0.0
Summary: Python implementation of the bitchat mesh networking protocol
License: Unlicense
Keywords: bitchat,mesh-networking,ble,encryption
Author: Nguyen Truong Long
Author-email: nguyentruonglongdev@gmail.com
Requires-Python: >=3.7,<4.0
Classifier: License :: OSI Approved
Classifier: Programming Language :: Python :: 3
Classifier: Programming Language :: Python :: 3.7
Classifier: Programming Language :: Python :: 3.8
Classifier: Programming Language :: Python :: 3.9
Classifier: Programming Language :: Python :: 3.10
Classifier: Programming Language :: Python :: 3.11
Classifier: Programming Language :: Python :: 3.12
Classifier: Programming Language :: Python :: 3.13
Requires-Dist: bleak (>=0.20.2,<0.21.0)
Requires-Dist: cryptography (>=42.0.5,<43.0.0)
Requires-Dist: pybloom-live (>=4.0.0,<5.0.0)
Project-URL: Homepage, https://github.com/nguyentruonglong/bitchat-py
Project-URL: Repository, https://github.com/nguyentruonglong/bitchat-py
